LICENSE
README.md
pyproject.toml
setup.py
marlin_kernels/__init__.py
marlin_kernels/scalar_type.py
marlin_kernels.egg-info/PKG-INFO
marlin_kernels.egg-info/SOURCES.txt
marlin_kernels.egg-info/dependency_links.txt
marlin_kernels.egg-info/requires.txt
marlin_kernels.egg-info/top_level.txt