Metadata-Version: 2.1
Name: marlin-kernels
Version: 0.3.6
Summary: Marlin quantization kernels
Author-email: Daniël de Kok <me@danieldk.eu>
Classifier: Programming Language :: Python :: 3.8
Classifier: Programming Language :: Python :: 3.9
Classifier: Programming Language :: Python :: 3.10
Classifier: Programming Language :: Python :: 3.11
Classifier: Programming Language :: Python :: 3.12
Classifier: License :: OSI Approved :: Apache Software License
Classifier: Topic :: Scientific/Engineering :: Artificial Intelligence
Classifier: Operating System :: OS Independent
Requires-Python: >=3.7
License-File: LICENSE
